n2_utils/__init__.py
n2_utils/base/__init__.py
n2_utils/base/models.py
n2_utils/bill/__init__.py
n2_utils/bill/constants.py
n2_utils/bill/models.py
n2_utils/bill/utils.py
n2_utils/customer/__init__.py
n2_utils/customer/models.py
n2_utils/customer/utils.py
n2_utils-0.2.5.dist-info/METADATA
n2_utils-0.2.5.dist-info/WHEEL
n2_utils-0.2.5.dist-info/top_level.txt
n2_utils-0.2.5.dist-info/RECORD
