Metadata-Version: 2.1
Name: n2_utils
Version: 0.2.5
Summary: N2 Common Area
Author: N2Mobil
Author-email: muslum.turk@n2mobil.com.tr
Classifier: Environment :: Web Environment
Classifier: Framework :: Django
Classifier: Intended Audience :: Developers
Classifier: License :: OSI Approved
Classifier: Programming Language :: Python :: 3
Classifier: Framework :: Django
Classifier: Framework :: Django :: 3.2
